rssi/__init__.py
rssi-1.0.0.dist-info/METADATA
rssi-1.0.0.dist-info/RECORD
rssi-1.0.0.dist-info/WHEEL
rssi-1.0.0.dist-info/top_level.txt
