Metadata-Version: 2.1
Name: rssi
Version: 1.0.0
Summary: Easy to use package for RSSI scanning and utilizing RSSI-based self-localization.
Home-page: https://jvillagomez@bitbucket.org/jvillagomez/rssi-module.git
Author: Juan Antonio Villlagomez
Author-email: email@juan-antonio.me
License: UNKNOWN
Platform: UNKNOWN
Classifier: License :: OSI Approved :: MIT License
Classifier: Operating System :: OS Independent
